dir_tree/__init__.py
dir_tree/generate_tree.py
dir_tree/main.py
dir_tree/save_tree_to_file.py
dir_tree_drh-1.4.dist-info/LICENSE
dir_tree_drh-1.4.dist-info/METADATA
dir_tree_drh-1.4.dist-info/WHEEL
dir_tree_drh-1.4.dist-info/entry_points.txt
dir_tree_drh-1.4.dist-info/top_level.txt
dir_tree_drh-1.4.dist-info/RECORD
