Metadata-Version: 2.1
Name: dir-tree-drh
Version: 1.4
Summary: Creating a directory tree is an efficient method for visually organizing your project's directory structure, complete with detailed information. It provides a clear model of your project layout for easy reference and management.
Home-page: https://github.com/dragon-devs/dir-tree-drh
Author: dragon-devs
Author-email: dragonfourtyseven@email.com
License: MIT
Classifier: Programming Language :: Python :: 3
Classifier: License :: OSI Approved :: MIT License
Classifier: Operating System :: OS Independent
License-File: LICENSE
